ansys/scade/wux/__init__.py
ansys/scade/wux/gowrapper.py
ansys/scade/wux/hooks.py
ansys/scade/wux/register.py
ansys/scade/wux/unregister.py
ansys/scade/wux/wux.py
ansys/scade/wux/wux.srg
ansys/scade/wux/wux23r1.srg
ansys/scade/wux/wux24r2.srg
ansys/scade/wux/wuxmodule.py
ansys/scade/wux/impl/a661.py
ansys/scade/wux/impl/dllext.py
ansys/scade/wux/impl/kcgcontext.py
ansys/scade/wux/impl/proxyext.py
ansys/scade/wux/impl/sdyext.py
ansys/scade/wux/impl/simuext.py
ansys/scade/wux/include/A661Connect.h
ansys/scade/wux/include/WuxA661Ext.h
ansys/scade/wux/include/WuxCtxExt.h
ansys/scade/wux/include/WuxDllExt.h
ansys/scade/wux/include/WuxSdyDll.h
ansys/scade/wux/include/WuxSdyExt.h
ansys/scade/wux/include/WuxSdyProxy.h
ansys/scade/wux/include/WuxSimuExt.h
ansys/scade/wux/lib/A661Connect.c
ansys/scade/wux/lib/WuxDllExt.cpp
ansys/scade/wux/lib/WuxGoMain.cpp
ansys/scade/wux/lib/WuxSdyProxy.cpp
ansys/scade/wux/lib/WuxSimuExt.cpp
ansys/scade/wux/res/CMakeLists.txt
ansys/scade/wux/test/sctoc_stub.py
ansys/scade/wux/test/utils.py
ansys_scade_wux-2.2.0.dist-info/entry_points.txt
ansys_scade_wux-2.2.0.dist-info/licenses/LICENSE
ansys_scade_wux-2.2.0.dist-info/WHEEL
ansys_scade_wux-2.2.0.dist-info/METADATA
ansys_scade_wux-2.2.0.dist-info/RECORD
