Metadata-Version: 2.4
Name: ansys-scade-wux
Version: 2.2.0
Summary: Generic code integration target for SCADE.
Keywords: Scade,Wrapper,Integration
Author-email: "ANSYS, Inc." <pyansys.core@ansys.com>
Maintainer-email: "ANSYS, Inc." <pyansys.core@ansys.com>
Requires-Python: >=3.7,!=3.8.*,!=3.9.*,<3.11
Classifier: Development Status :: 4 - Beta
Classifier: Programming Language :: Python :: 3
Classifier: License :: OSI Approved :: MIT License
Classifier: Operating System :: Microsoft :: Windows
License-File: LICENSE
Requires-Dist: importlib-metadata >= 1.0; python_version < '3.8'
Requires-Dist: importlib-metadata >= 4.0; python_version >= '3.8'
Requires-Dist: ansys-scade-apitools
Requires-Dist: build==1.2.2.post1 ; extra == "build"
Requires-Dist: twine==6.1.0 ; extra == "build"
Requires-Dist: ansys-sphinx-theme[autoapi]==1.5.3 ; extra == "doc"
Requires-Dist: autodoc_pydantic==2.2.0 ; extra == "doc"
Requires-Dist: numpydoc==1.8.0 ; extra == "doc"
Requires-Dist: sphinx==8.1.3 ; extra == "doc"
Requires-Dist: sphinx-autodoc-typehints==2.3.0 ; extra == "doc"
Requires-Dist: sphinxcontrib-globalsubs==0.1.2 ; extra == "doc"
Requires-Dist: sphinxcontrib-httpdomain==1.8.1 ; extra == "doc"
Requires-Dist: sphinx-copybutton==0.5.2 ; extra == "doc"
Requires-Dist: sphinxnotes-strike==1.2.1 ; extra == "doc"
Requires-Dist: breathe>=4.33.1 ; extra == "doc"
Requires-Dist: pytest==8.4.1 ; extra == "tests"
Requires-Dist: pytest-cov==6.2.1 ; extra == "tests"
Project-URL: Discussions, https://github.com/ansys/scade-wux/discussions
Project-URL: Documentation, https://wux.scade.docs.pyansys.com
Project-URL: Homepage, https://www.ansys.com/products/embedded-software/ansys-scade-suite
Project-URL: Issues, https://github.com/ansys/scade-wux/issues
Project-URL: Releases, https://github.com/ansys/scade-wux/releases
Project-URL: Source, https://github.com/ansys/scade-wux
Provides-Extra: build
Provides-Extra: doc
Provides-Extra: tests
